alo/__init__.py
alo/__version__.py
alo/alo.py
alo/exceptions.py
alo/logger.py
alo/main.py
alo/model.py
alo/solution_register.py
alo/utils.py
alo/yml_schema.py
alo/ConfigFormats/aws_codebuild_buildspec_format.yaml
alo/ConfigFormats/aws_codebuild_s3_project_format.json
alo/ConfigFormats/experimental_plan.yaml
alo/ConfigFormats/experimental_plan_format.yaml
alo/Dockerfiles/SagemakerDockerfile
alo/Dockerfiles/main.py
alo/Dockerfiles/requirements.txt
alo/Dockerfiles/register/Dockerfile
alo/Dockerfiles/register/dockerfile_cpu/Dockerfile
alo/Dockerfiles/register/dockerfile_gpu/Dockerfile
alo/api/__init__.py
alo/api/api_server.py
alo/api/error_handlers.py
alo/api/file_handlers.py
alo/api/models.py
alo/api/validators.py
alo/config/ai_conductor_api.json
alo/config/redis_error_table.json
alo/example/setting/infra_config.yaml
alo/example/setting/sagemaker_config.yaml
alo/example/setting/solution_info.yaml
alo/example/titanic/experimental_plan.yaml
alo/example/titanic/titanic.py
alo/example/titanic/inference_dataset/inference_dataset.csv
alo/example/titanic/setting/infra_config.yaml
alo/example/titanic/setting/sagemaker_config.yaml
alo/example/titanic/setting/solution_info.yaml
alo/example/titanic/train_dataset/train.csv
template/setting/infra_config.yaml
template/setting/solution_info.yaml
mellerikat_alo-3.0.4.dist-info/METADATA
mellerikat_alo-3.0.4.dist-info/WHEEL
mellerikat_alo-3.0.4.dist-info/entry_points.txt
mellerikat_alo-3.0.4.dist-info/top_level.txt
mellerikat_alo-3.0.4.dist-info/RECORD
