Metadata-Version: 2.4
Name: mellerikat-alo
Version: 3.0.4
Summary: ALO (AI Learning Organizer)
Home-page: https://mellerikat.com
Author: LGE
Author-email: mellerikat@lge.com
License: LGE License
Platform: Linux
Platform: FreeBSD
Platform: Solaris
Classifier: Development Status :: 3 - Alpha
Classifier: Intended Audience :: Developers
Classifier: Programming Language :: Python
Classifier: Programming Language :: Python :: 3
Requires-Python: >=3.7
Requires-Dist: gitpython>=3.1.43
Requires-Dist: pyyaml>=6.0.1
Requires-Dist: pytz>=2021.3
Requires-Dist: boto3==1.33.13; python_version <= "3.7"
Requires-Dist: boto3==1.34.19; python_version > "3.7"
Requires-Dist: botocore==1.33.13; python_version <= "3.7"
Requires-Dist: botocore==1.34.19; python_version > "3.7"
Requires-Dist: psutil>=5.9.5
Requires-Dist: requests>=2.31.0
Requires-Dist: redis>=5.0.1
Requires-Dist: docker>=7.0.0; python_version > "3.7"
Requires-Dist: docker==6.1.3; python_version <= "3.7"
Requires-Dist: tabulate>=0.9.0
Requires-Dist: colorama>=0.4.6
Requires-Dist: pyfiglet==0.8.post1; python_version <= "3.8"
Requires-Dist: pyfiglet==1.0.2; python_version > "3.8"
Requires-Dist: pydantic==2.5.3; python_version <= "3.7"
Requires-Dist: pydantic>=2.7.4; python_version > "3.7"
Requires-Dist: pydantic-settings==2.0.3; python_version <= "3.7"
Requires-Dist: pydantic-settings>=2.3.3; python_version > "3.7"
Requires-Dist: google-cloud-storage==2.18.2
Requires-Dist: uvicorn==0.32.1
Requires-Dist: fastapi==0.115.5
Requires-Dist: python-multipart==0.0.20
Requires-Dist: numpy==1.26.1
Requires-Dist: pillow
Dynamic: author
Dynamic: author-email
Dynamic: classifier
Dynamic: description
Dynamic: home-page
Dynamic: license
Dynamic: platform
Dynamic: requires-dist
Dynamic: requires-python
Dynamic: summary
